tweetstash/__init__.py
tweetstash/__main__.py
tweetstash/cli.py
tweetstash/search.py
tweetstash/stash.py
tweetstash-0.1.3.dist-info/DESCRIPTION.rst
tweetstash-0.1.3.dist-info/METADATA
tweetstash-0.1.3.dist-info/RECORD
tweetstash-0.1.3.dist-info/WHEEL
tweetstash-0.1.3.dist-info/entry_points.txt
tweetstash-0.1.3.dist-info/metadata.json
tweetstash-0.1.3.dist-info/top_level.txt
